MANIFEST.in
README.txt
plonetheme.notredame-configure.zcml
setup.cfg
setup.py
docs/HISTORY.txt
docs/INSTALL.txt
docs/LICENSE.GPL
docs/LICENSE.txt
plonetheme/__init__.py
plonetheme.notredame.egg-info/PKG-INFO
plonetheme.notredame.egg-info/SOURCES.txt
plonetheme.notredame.egg-info/dependency_links.txt
plonetheme.notredame.egg-info/entry_points.txt
plonetheme.notredame.egg-info/namespace_packages.txt
plonetheme.notredame.egg-info/not-zip-safe
plonetheme.notredame.egg-info/requires.txt
plonetheme.notredame.egg-info/top_level.txt
plonetheme/notredame/TODO.txt
plonetheme/notredame/__init__.py
plonetheme/notredame/configure.zcml
plonetheme/notredame/profiles.zcml
plonetheme/notredame/setuphandlers.py
plonetheme/notredame/skins.zcml
plonetheme/notredame/tests.py
plonetheme/notredame/browser/__init__.py
plonetheme/notredame/browser/configure.zcml
plonetheme/notredame/browser/interfaces.py
plonetheme/notredame/browser/viewlet.pt
plonetheme/notredame/browser/viewlets.py
plonetheme/notredame/browser/images/README.txt
plonetheme/notredame/browser/images/arrow-darkblue.gif
plonetheme/notredame/browser/images/arrow-darkblue.png
plonetheme/notredame/browser/images/arrow-darkblue_down.gif
plonetheme/notredame/browser/images/arrow-darkblue_down.png
plonetheme/notredame/browser/images/arrow-darkblue_rtl.gif
plonetheme/notredame/browser/images/arrow-darkblue_rtl.png
plonetheme/notredame/browser/images/arrow-gray-bread.gif
plonetheme/notredame/browser/images/arrow-gray-bread.png
plonetheme/notredame/browser/images/arrow-gray-bread_rtl.gif
plonetheme/notredame/browser/images/arrow-gray-bread_rtl.png
plonetheme/notredame/browser/images/arrow-gray.gif
plonetheme/notredame/browser/images/arrow-gray.png
plonetheme/notredame/browser/images/arrow-gray_rtl.gif
plonetheme/notredame/browser/images/arrow-gray_rtl.png
plonetheme/notredame/browser/images/background_slice.png
plonetheme/notredame/browser/images/global-tabs-gray.gif
plonetheme/notredame/browser/images/global-tabs-gray.png
plonetheme/notredame/browser/images/plone-icon-background.gif
plonetheme/notredame/browser/images/plone-icon-background.png
plonetheme/notredame/browser/images/transparent.gif
plonetheme/notredame/browser/images/transparent.png
plonetheme/notredame/browser/stylesheets/README.txt
plonetheme/notredame/browser/stylesheets/calendar.css
