Metadata-Version: 1.0
Name: plonetheme.notredame
Version: 1.0.3
Summary: Theme for Plone 3 with color scheme based on new Plone Logo
Home-page: http://svn.plone.org/svn/collective/plonetheme.notredame
Author: Harito Reisman, Christian Schneider
Author-email: notredame@haritomedia.com
License: GPL
Keywords: web zope plone theme
Platform: UNKNOWN
Classifier: Framework :: Plone
Classifier: Programming Language :: Python
Classifier: Topic :: Software Development :: Libraries :: Python Modules
